aioclock/__init__.py
aioclock/api.py
aioclock/app.py
aioclock/custom_types.py
aioclock/exceptions.py
aioclock/group.py
aioclock/logger.py
aioclock/provider.py
aioclock/py.typed
aioclock/task.py
aioclock/triggers.py
aioclock/utils.py
aioclock/ext/__init__.py
aioclock/ext/fast.py
aioclock-0.3.0.dist-info/METADATA
aioclock-0.3.0.dist-info/WHEEL
aioclock-0.3.0.dist-info/licenses/LICENSE
aioclock-0.3.0.dist-info/RECORD
