Metadata-Version: 2.3
Name: aioclock
Version: 0.3.0
Summary: An asyncio-based scheduling framework designed for execution of periodic task with integrated support for dependency injection, enabling efficient and flexible task management
Project-URL: repository, https://github.com/ManiMozaffar/aioclock
Project-URL: Homepage, https://github.com/ManiMozaffar/aioclock
Project-URL: Documentation, https://github.com/ManiMozaffar/aioclock
Project-URL: Source, https://github.com/ManiMozaffar/aioclock
Author-email: Mani Mozaffar <mani.mozaffar@gmail.com>
License-Expression: MIT
License-File: LICENSE
Requires-Python: >=3.8
Requires-Dist: asyncer>=0.0.7
Requires-Dist: croniter>=2.0.5
Requires-Dist: fast-depends>=2.4.0
Requires-Dist: pydantic<3.0,>2.5
Provides-Extra: fastapi
Requires-Dist: fastapi; extra == 'fastapi'
